ifctester/__init__.py
ifctester/__main__.py
ifctester/facet.py
ifctester/ids.py
ifctester/ids.xsd
ifctester/reporter.py
ifctester/templates/report.html
ifctester-0.8.3.dist-info/METADATA
ifctester-0.8.3.dist-info/WHEEL
ifctester-0.8.3.dist-info/top_level.txt
ifctester-0.8.3.dist-info/RECORD
